<?xml version="1.0" encoding="utf-8"?>
<LanguageData>
  <!--The following translations were generated by https://www.deepl.com/-->
  <!-- EN: Special Police Armor -->
  <JRA_Police_Armor.label>Spezielle Polizei-Rüstung</JRA_Police_Armor.label>
  <!-- EN: A heavy suit of armor designed to withstand a great deal of ballistic and environmental damage, suited for urban and close-quarters combat. -->
  <JRA_Police_Armor.description>Eine schwere Rüstung, die entwickelt wurde, um einer großen Menge an ballistischem und umweltbedingtem Schaden zu widerstehen, geeignet für den Stadt- und Nahkampf.</JRA_Police_Armor.description>
  <!-- EN: Special Police Helmet -->
  <JRA_Police_Helmet.label>Spezial-Polizei-Helm</JRA_Police_Helmet.label>
  <!-- EN: While this helmet provides excellent full head protection, its unspoken use is for intimidation. Cold to the touch. -->
  <JRA_Police_Helmet.description>Dieser Helm bietet zwar einen ausgezeichneten Vollkopfschutz, dient aber unausgesprochen der Einschüchterung. Fühlt sich kalt an.</JRA_Police_Helmet.description>
</LanguageData>
